odoo/addons/pos_default_partner/README.rst
odoo/addons/pos_default_partner/__init__.py
odoo/addons/pos_default_partner/__manifest__.py
odoo/addons/pos_default_partner/i18n/es.po
odoo/addons/pos_default_partner/i18n/fr.po
odoo/addons/pos_default_partner/i18n/it.po
odoo/addons/pos_default_partner/i18n/pos_default_partner.pot
odoo/addons/pos_default_partner/models/__init__.py
odoo/addons/pos_default_partner/models/pos_config.py
odoo/addons/pos_default_partner/models/pos_order.py
odoo/addons/pos_default_partner/models/res_config_settings.py
odoo/addons/pos_default_partner/readme/CONFIGURE.rst
odoo/addons/pos_default_partner/readme/CONTRIBUTORS.rst
odoo/addons/pos_default_partner/readme/DESCRIPTION.rst
odoo/addons/pos_default_partner/static/description/icon.png
odoo/addons/pos_default_partner/static/description/index.html
odoo/addons/pos_default_partner/static/src/js/models.esm.js
odoo/addons/pos_default_partner/tests/__init__.py
odoo/addons/pos_default_partner/tests/test_pos_default_partner.py
odoo/addons/pos_default_partner/views/res_config_settings_view.xml
odoo_addon_pos_default_partner-16.0.1.0.2.dist-info/METADATA
odoo_addon_pos_default_partner-16.0.1.0.2.dist-info/WHEEL
odoo_addon_pos_default_partner-16.0.1.0.2.dist-info/top_level.txt
odoo_addon_pos_default_partner-16.0.1.0.2.dist-info/RECORD
